netbox_routeros/__init__.py
netbox_routeros/__version__.py
netbox_routeros/api/__init__.py
netbox_routeros/api/serializers/__init__.py
netbox_routeros/api/serializers/_generic.py
netbox_routeros/api/serializers/capsman.py
netbox_routeros/api/serializers/interface.py
netbox_routeros/api/serializers/routeros.py
netbox_routeros/api/urls.py
netbox_routeros/api/views/__init__.py
netbox_routeros/api/views/capsman.py
netbox_routeros/api/views/interface.py
netbox_routeros/api/views/proxy/__init__.py
netbox_routeros/api/views/proxy/dcim.py
netbox_routeros/api/views/routeros.py
netbox_routeros/filtersets/__init__.py
netbox_routeros/filtersets/capsman.py
netbox_routeros/filtersets/interface.py
netbox_routeros/filtersets/routeros.py
netbox_routeros/forms/__init__.py
netbox_routeros/forms/_fields.py
netbox_routeros/forms/capsman.py
netbox_routeros/forms/interface.py
netbox_routeros/forms/routeros.py
netbox_routeros/migrations/0001_initial.py
netbox_routeros/migrations/0002_alter_capsmanchannel_capsman_capsmanserverconfig.py
netbox_routeros/migrations/0003_interfacelist_capsmanserverconfig_interface_lists.py
netbox_routeros/migrations/0004_capsmanaccesslistitem.py
netbox_routeros/migrations/__init__.py
netbox_routeros/models/__init__.py
netbox_routeros/models/_fields.py
netbox_routeros/models/capsman.py
netbox_routeros/models/interface.py
netbox_routeros/models/proxy/__init__.py
netbox_routeros/models/proxy/dcim.py
netbox_routeros/models/routeros.py
netbox_routeros/navigation.py
netbox_routeros/py.typed
netbox_routeros/tables/__init__.py
netbox_routeros/tables/capsman.py
netbox_routeros/tables/interface.py
netbox_routeros/tables/routeros.py
netbox_routeros/templates/netbox_routeros/core/generic-object.html
netbox_routeros/urls.py
netbox_routeros/validators/__init__.py
netbox_routeros/views/__init__.py
netbox_routeros/views/capsman.py
netbox_routeros/views/interface.py
netbox_routeros/views/routeros.py
netbox_routeros-0.0.4.dist-info/LICENSE
netbox_routeros-0.0.4.dist-info/METADATA
netbox_routeros-0.0.4.dist-info/WHEEL
netbox_routeros-0.0.4.dist-info/RECORD
