Metadata-Version: 2.3
Name: netbox-routeros
Version: 0.0.4
Summary: RouterOS plugin
License: MIT
Keywords: netbox,routeros,plugin
Author: Slowaner
Author-email: slowaner@slowaner.ru
Requires-Python: >=3.10.0,<4.0
Classifier: Development Status :: 4 - Beta
Classifier: Framework :: Django
Classifier: License :: OSI Approved :: MIT License
Classifier: Natural Language :: English
Classifier: Programming Language :: Python :: 3
Classifier: Programming Language :: Python :: 3.10
Classifier: Programming Language :: Python :: 3.11
Classifier: Programming Language :: Python :: 3.12
Classifier: Programming Language :: Python :: 3.13
Classifier: Programming Language :: Python :: 3 :: Only
Provides-Extra: dev
Provides-Extra: docs
Provides-Extra: lint
Provides-Extra: test
Requires-Dist: black (==23.11.0) ; extra == "lint"
Requires-Dist: django (==5.1.5) ; extra == "dev"
Requires-Dist: django (==5.1.5) ; extra == "test"
Requires-Dist: django-tables2 (==2.7.5) ; extra == "dev"
Requires-Dist: djangorestframework (==3.15.2) ; extra == "dev"
Requires-Dist: flake8 (==6.1.0) ; extra == "lint"
Requires-Dist: isort (==5.12.0) ; extra == "lint"
Requires-Dist: jinja2 (==3.1.5) ; extra == "dev"
Requires-Dist: mypy (==1.15.0) ; extra == "lint"
Requires-Dist: netaddr (>=1.3.0,<1.4.0) ; extra == "dev"
Requires-Dist: netaddr (>=1.3.0,<1.4.0) ; extra == "test"
Requires-Dist: pytest (>=7.4.3,<8) ; extra == "test"
Requires-Dist: tbump (==6.11.0) ; extra == "dev"
Requires-Dist: types-netaddr (>=1.3.0,<1.4.0) ; extra == "lint"
Project-URL: Bug Tracker, https://sourcecraft.dev/slowaner/netbox-routeros/issues
Project-URL: Documentation, https://sourcecraft.dev/slowaner/netbox-routeros
Project-URL: Homepage, https://sourcecraft.dev/slowaner/netbox-routeros
Project-URL: Repository, https://sourcecraft.dev/slowaner/netbox-routeros
